parade/__init__.py
parade/command/server.py
parade/server/__init__.py
parade/server/api/__init__.py
parade/server/api/data.py
parade/server/api/exec.py
parade/server/api/flow.py
parade/server/api/task.py
parade/server/auth/__init__.py
parade/server/auth/api.py
parade/server/dash/__init__.py
parade/server/dash/chart/__init__.py
parade/server/dash/chart/choropleth.py
parade/server/dash/chart/gantt.py
parade/server/dash/chart/indicator.py
parade/server/dash/chart/radar.py
parade/server/dash/filter/__init__.py
parade/server/dash/filter/date_range.py
parade/server/dash/filter/date_single.py
parade/server/dash/filter/selector.py
parade/server/dash/table/__init__.py
parade/server/dash/table/core.py
parade/server/dash/utils/__init__.py
parade_server-0.0.2.1.dist-info/LICENSE
parade_server-0.0.2.1.dist-info/METADATA
parade_server-0.0.2.1.dist-info/WHEEL
parade_server-0.0.2.1.dist-info/top_level.txt
parade_server-0.0.2.1.dist-info/RECORD
