Metadata-Version: 2.1
Name: parade-server
Version: 0.0.2.1
Summary: A server module of parade
Home-page: https://github.com/bailaohe/parade-server
Author: He Bai
Author-email: bailaohe@gmail.com
License: UNKNOWN
Keywords: parade,feature
Platform: any
Classifier: Development Status :: 4 - Beta
Classifier: Intended Audience :: Developers
Classifier: License :: OSI Approved :: Apache Software License
Classifier: Programming Language :: Python :: 3
Classifier: Topic :: Database
Classifier: Topic :: Software Development :: Libraries :: Python Modules
Classifier: Operating System :: Unix
Classifier: Operating System :: MacOS :: MacOS X
Classifier: Operating System :: Microsoft :: Windows
Classifier: Operating System :: POSIX
Requires-Python: >=3.4
Requires-Dist: flask
Requires-Dist: flask-cors
Requires-Dist: flask-restful
Requires-Dist: Flask-SocketIO
Requires-Dist: flask-login
Requires-Dist: parade
Requires-Dist: arrow
Requires-Dist: cerberus
Requires-Dist: palettable
Provides-Extra: dash
Requires-Dist: dash ; extra == 'dash'
Requires-Dist: dash-html-components ; extra == 'dash'
Requires-Dist: dash-core-components ; extra == 'dash'
Requires-Dist: dash-table ; extra == 'dash'
Requires-Dist: flask-caching ; extra == 'dash'
